certbot_dns_leaseweb/__init__.py
certbot_dns_leaseweb/client.py
certbot_dns_leaseweb/plugin.py
certbot_dns_leaseweb/utils.py
certbot_dns_leaseweb-1.0.3.dist-info/licenses/LICENSE
certbot_dns_leaseweb-1.0.3.dist-info/METADATA
certbot_dns_leaseweb-1.0.3.dist-info/WHEEL
certbot_dns_leaseweb-1.0.3.dist-info/entry_points.txt
certbot_dns_leaseweb-1.0.3.dist-info/top_level.txt
certbot_dns_leaseweb-1.0.3.dist-info/RECORD
