Metadata-Version: 2.4
Name: certbot-dns-leaseweb
Version: 1.0.3
Summary: Automate dns-01 challenge completion using Leaseweb Domains API.
Author-email: iwaseatenbyagrue <iwaseatenbyagrue@gmail.com>
License: Apache License 2.0
Project-URL: Homepage, https://gitlab.com/iwaseatenbyagrue/certbot-dns-leaseweb
Project-URL: Repository, https://gitlab.com/iwaseatenbyagrue/certbot-dns-leaseweb
Keywords: certbot,leaseweb,dns-01
Classifier: Programming Language :: Python :: 3
Requires-Python: >=3.8
License-File: LICENSE
Requires-Dist: certbot>=2.7.1
Requires-Dist: requests
Requires-Dist: urllib3>=2.0.7
Provides-Extra: dev
Requires-Dist: black; extra == "dev"
Requires-Dist: pylint; extra == "dev"
Provides-Extra: test
Requires-Dist: bandit; extra == "test"
Requires-Dist: coverage; extra == "test"
Requires-Dist: requests-mock; extra == "test"
Dynamic: license-file
